pymigrate/__init__.py
pymigrate/deps_handler.py
pymigrate/env.py
pymigrate/main.py
pymigrate/parser_import.py
pymigrate/walk.py
py_migrate-0.1.1.dist-info/LICENSE
py_migrate-0.1.1.dist-info/METADATA
py_migrate-0.1.1.dist-info/WHEEL
py_migrate-0.1.1.dist-info/entry_points.txt
py_migrate-0.1.1.dist-info/top_level.txt
py_migrate-0.1.1.dist-info/RECORD
