Metadata-Version: 2.1
Name: py-migrate
Version: 0.1.1
Summary: Transform python codebase to a virtual environment
Home-page: https://github.com/Narasimha1997/pyMigrate
Author: Narasimha Prasanna HN
Author-email: narasimhaprasannahn@gmail.com
License: MIT
Keywords: python venv automation
Platform: UNKNOWN
Classifier: Programming Language :: Python :: 3
Classifier: License :: OSI Approved :: MIT License
Classifier: Operating System :: OS Independent
Requires-Dist: simple-term-menu (==0.10.5)
